pymodbus_repl/.DS_Store
pymodbus_repl/README.rst
pymodbus_repl/__init__.py
pymodbus_repl/client/README.md
pymodbus_repl/client/__init__.py
pymodbus_repl/client/main.py
pymodbus_repl/client/mclient.py
pymodbus_repl/lib/__init__.py
pymodbus_repl/lib/completer.py
pymodbus_repl/lib/helper.py
pymodbus_repl/lib/reactive.py
pymodbus_repl/server/README.md
pymodbus_repl/server/__init__.py
pymodbus_repl/server/cli.py
pymodbus_repl/server/main.py
pymodbus_repl-2.0.3.dist-info/LICENSE
pymodbus_repl-2.0.3.dist-info/METADATA
pymodbus_repl-2.0.3.dist-info/WHEEL
pymodbus_repl-2.0.3.dist-info/entry_points.txt
pymodbus_repl-2.0.3.dist-info/RECORD
