Metadata-Version: 2.1
Name: pymodbus_repl
Version: 2.0.3
Summary: REPL (Read-Eval-Print Loop) tool for working with Modbus devices using the Pymodbus library.
Home-page: https://github.com/pymodbus-dev/repl
Author: dhoomakethu
Author-email: otlasanju@gmail.com
Requires-Python: >=3.8,<4.0
Classifier: Programming Language :: Python :: 3
Classifier: Programming Language :: Python :: 3.8
Classifier: Programming Language :: Python :: 3.9
Classifier: Programming Language :: Python :: 3.10
Classifier: Programming Language :: Python :: 3.11
Classifier: Programming Language :: Python :: 3.12
Requires-Dist: aiohttp (>=3.8.6) ; python_version < "3.12"
Requires-Dist: aiohttp (>=3.9.0b0) ; python_version == "3.12"
Requires-Dist: prompt-toolkit (>=3.0.43,<4.0.0)
Requires-Dist: pygments (>=2.17.2,<3.0.0)
Requires-Dist: tabulate (>=0.9.0,<0.10.0)
Requires-Dist: typer[all] (>=0.9.0,<0.10.0)
Project-URL: Repository, https://github.com/pymodbus-dev/repl
